mohand/__init__.py
mohand/__main__.py
mohand/decorator.py
mohand/exception.py
mohand/hands.py
mohand/load_file.py
mohand/state.py
mohand/utils.py
mohand/version.py
mohand/cli/__init__.py
mohand/cli/command.py
mohand/cli/options.py
mohand/vendor/__init__.py
mohand/vendor/crayons.py
mohand/vendor/prettytable.py
mohand/vendor/six.py
mohand/vendor/click/__init__.py
mohand/vendor/click/_bashcomplete.py
mohand/vendor/click/_compat.py
mohand/vendor/click/_termui_impl.py
mohand/vendor/click/_textwrap.py
mohand/vendor/click/_unicodefun.py
mohand/vendor/click/_winconsole.py
mohand/vendor/click/core.py
mohand/vendor/click/decorators.py
mohand/vendor/click/exceptions.py
mohand/vendor/click/formatting.py
mohand/vendor/click/globals.py
mohand/vendor/click/parser.py
mohand/vendor/click/termui.py
mohand/vendor/click/testing.py
mohand/vendor/click/types.py
mohand/vendor/click/utils.py
mohand/vendor/click_completion/__init__.py
mohand/vendor/click_completion/core.py
mohand/vendor/click_completion/lib.py
mohand/vendor/click_completion/patch.py
mohand/vendor/click_didyoumean/__init__.py
mohand/vendor/click_help_colors/__init__.py
mohand/vendor/colorama/__init__.py
mohand/vendor/colorama/ansi.py
mohand/vendor/colorama/ansitowin32.py
mohand/vendor/colorama/initialise.py
mohand/vendor/colorama/win32.py
mohand/vendor/colorama/winterm.py
mohand/vendor/easydict/__init__.py
mohand/vendor/enum/__init__.py
mohand/vendor/jinja2/__init__.py
mohand/vendor/jinja2/_compat.py
mohand/vendor/jinja2/_identifier.py
mohand/vendor/jinja2/asyncfilters.py
mohand/vendor/jinja2/asyncsupport.py
mohand/vendor/jinja2/bccache.py
mohand/vendor/jinja2/compiler.py
mohand/vendor/jinja2/constants.py
mohand/vendor/jinja2/debug.py
mohand/vendor/jinja2/defaults.py
mohand/vendor/jinja2/environment.py
mohand/vendor/jinja2/exceptions.py
mohand/vendor/jinja2/ext.py
mohand/vendor/jinja2/filters.py
mohand/vendor/jinja2/idtracking.py
mohand/vendor/jinja2/lexer.py
mohand/vendor/jinja2/loaders.py
mohand/vendor/jinja2/meta.py
mohand-1.2.0.dist-info/LICENSE
mohand-1.2.0.dist-info/METADATA
mohand-1.2.0.dist-info/WHEEL
mohand-1.2.0.dist-info/entry_points.txt
mohand-1.2.0.dist-info/top_level.txt
mohand-1.2.0.dist-info/RECORD
