Metadata-Version: 2.1
Name: mohand
Version: 1.2.0
Summary: 通用自动化处理工具
Home-page: https://github.com/littlemo/mohand
Author: moear developers
Author-email: moore@moorehy.com
Maintainer: littlemo
Maintainer-email: moore@moorehy.com
License: GPLv3
Project-URL: Source, https://github.com/littlemo/mohand
Project-URL: Documentation, http://mohand.rtfd.io/
Project-URL: Tracker, https://github.com/littlemo/mohand/issues
Keywords: mohand cli automation
Platform: UNKNOWN
Classifier: Development Status :: 4 - Beta
Classifier: Environment :: Console
Classifier: Environment :: MacOS X
Classifier: Intended Audience :: Developers
Classifier: License :: OSI Approved :: GNU General Public License v3 (GPLv3)
Classifier: Natural Language :: Chinese (Simplified)
Classifier: Operating System :: MacOS
Classifier: Operating System :: POSIX :: Linux
Classifier: Programming Language :: Python
Classifier: Programming Language :: Python :: 2
Classifier: Programming Language :: Python :: 2.7
Classifier: Programming Language :: Python :: 3
Classifier: Programming Language :: Python :: 3.5
Classifier: Topic :: Communications :: Email
Classifier: Topic :: Documentation :: Sphinx
Classifier: Topic :: Software Development :: Testing :: Unit
Classifier: Topic :: Software Development :: Libraries :: Python Modules
Classifier: Topic :: Software Development :: User Interfaces
Classifier: Topic :: Software Development :: Version Control :: Git
Classifier: Topic :: Terminals
Classifier: Topic :: Text Editors :: Emacs
Classifier: Topic :: Utilities
Requires-Python: >=2.7
Requires-Dist: stevedore (>=1.28.0)
